ja_stopword_remover/__init__.py
ja_stopword_remover/remover.py
ja_stopword_remover/stop_words.py
ja_stopword_remover-0.2.4.dist-info/METADATA
ja_stopword_remover-0.2.4.dist-info/WHEEL
ja_stopword_remover-0.2.4.dist-info/top_level.txt
ja_stopword_remover-0.2.4.dist-info/RECORD
