Metadata-Version: 2.1
Name: ja-stopword-remover
Version: 0.2.4
Summary: 形態素解析後の日本語の文のリストからストップワードを除去するためのモジュール
Home-page: https://pickerlab.net/
Author: picker.
Author-email: picker@pickerlav.jp
License: MIT
Platform: UNKNOWN
